langgraph_opensearch_store/__init__.py
langgraph_opensearch_store/checkpointer.py
langgraph_opensearch_store/cli.py
langgraph_opensearch_store/client.py
langgraph_opensearch_store/config.py
langgraph_opensearch_store/schema.py
langgraph_opensearch_store/store.py
langgraph_opensearch_store-0.1.8.dist-info/WHEEL
langgraph_opensearch_store-0.1.8.dist-info/entry_points.txt
langgraph_opensearch_store-0.1.8.dist-info/METADATA
langgraph_opensearch_store-0.1.8.dist-info/RECORD
