Metadata-Version: 2.3
Name: langgraph-opensearch-store
Version: 0.1.8
Summary: LangGraph BaseStore implementation backed by OpenSearch with Pydantic configuration.
Author: NTTDATA China Team
Author-email: NTTDATA China Team <unidotnet@gmail.com>
License: Apache-2.0
Classifier: License :: OSI Approved :: Apache Software License
Classifier: Programming Language :: Python :: 3
Classifier: Programming Language :: Python :: 3.11
Classifier: Operating System :: OS Independent
Requires-Dist: langgraph>=1.0
Requires-Dist: langchain-core>=1.0
Requires-Dist: langchain-openai>=1.0
Requires-Dist: opensearch-py>=2.6
Requires-Dist: pydantic>=2.12
Requires-Dist: pydantic-settings>=2.12
Requires-Dist: click>=8.1
Requires-Dist: boto3>=1.40 ; extra == 'aws'
Requires-Dist: requests-aws4auth>=1.3 ; extra == 'aws'
Requires-Dist: pytest>=9.0 ; extra == 'dev'
Requires-Dist: ruff>=0.14 ; extra == 'dev'
Requires-Dist: pyright>=1.1 ; extra == 'dev'
Requires-Dist: psycopg[binary,pool]>=3.2 ; extra == 'system'
Requires-Dist: langgraph-checkpoint-postgres>=3.0 ; extra == 'system'
Requires-Python: >=3.11
Provides-Extra: aws
Provides-Extra: dev
Provides-Extra: system
